cry_vs/HTTPHelper.py
cry_vs/__init__.py
cry_vs/client.py
cry_vs/emitter.py
cry_vs/exceptions.py
cry_vs.py-0.0.0.12.dist-info/LICENSE
cry_vs.py-0.0.0.12.dist-info/METADATA
cry_vs.py-0.0.0.12.dist-info/WHEEL
cry_vs.py-0.0.0.12.dist-info/top_level.txt
cry_vs.py-0.0.0.12.dist-info/RECORD
