Metadata-Version: 2.1
Name: cry-vs.py
Version: 0.0.0.12
Summary: A Crypto-Versus wrapper
Home-page: https://github.com/AW1534/cry-vs.py
Author: addikted
Author-email: addiktedmontage@gmail.com
License: UNKNOWN
Project-URL: Documentation, https://cry-vs-py.readthedocs.io/en/latest/
Project-URL: Bug Tracker, https://github.com/AW1534/cry-vs.py/issues
Platform: UNKNOWN
Classifier: Programming Language :: Python :: 3
Classifier: License :: OSI Approved :: GNU Affero General Public License v3
Classifier: Operating System :: OS Independent
Classifier: Development Status :: 2 - Pre-Alpha
Classifier: Natural Language :: English
Classifier: Topic :: Internet :: WWW/HTTP
Requires-Python: >=3.6
License-File: LICENSE
Requires-Dist: requests (>=2.27.1)
